cmtr/__init__.py
cmtr/cli.py
cmtr/codex_client.py
cmtr/config.py
cmtr/core.py
cmtr/errors.py
cmtr/git.py
cmtr/hook.py
cmtr/openai_client.py
cmtr/prompt.py
cmtr/py.typed
cmtr/ui.py
cmtr-0.3.0.dist-info/WHEEL
cmtr-0.3.0.dist-info/entry_points.txt
cmtr-0.3.0.dist-info/METADATA
cmtr-0.3.0.dist-info/RECORD
