Metadata-Version: 2.3
Name: cmtr
Version: 0.3.0
Summary: AI-powered git commit message generator
Keywords: git,commit,cli,openai,automation
Author: Shayne Sweeney
Author-email: Shayne Sweeney <79330+shayne@users.noreply.github.com>
License: MIT License
Classifier: Development Status :: 3 - Alpha
Classifier: Environment :: Console
Classifier: Intended Audience :: Developers
Classifier: License :: OSI Approved :: MIT License
Classifier: Programming Language :: Python :: 3
Classifier: Programming Language :: Python :: 3 :: Only
Classifier: Programming Language :: Python :: 3.12
Classifier: Programming Language :: Python :: 3.13
Classifier: Topic :: Software Development :: Version Control
Classifier: Topic :: Utilities
Requires-Dist: openai>=2.14.0
Requires-Dist: rich>=14.2.0
Requires-Dist: typer>=0.21.0
Requires-Python: >=3.12
Project-URL: Homepage, https://github.com/shayne/cmtr
Project-URL: Issues, https://github.com/shayne/cmtr/issues
Project-URL: Repository, https://github.com/shayne/cmtr
